jax/cs/storage/__init__.py
jax/cs/storage/base.py
jax/cs/storage/cache/__init__.py
jax/cs/storage/cache/object_cache.py
jax/cs/storage/config.py
jax/cs/storage/entrypoint.py
jax/cs/storage/enums.py
jax/cs/storage/exceptions.py
jax/cs/storage/future/__init__.py
jax/cs/storage/future/exceptions.py
jax/cs/storage/future/localizer.py
jax/cs/storage/future/protocols.py
jax/cs/storage/object/__init__.py
jax/cs/storage/object/abstract.py
jax/cs/storage/object/services/__init__.py
jax/cs/storage/object/services/gcs/__init__.py
jax/cs/storage/object/services/gcs/service.py
jax/cs/storage/object/services/gcs/utils.py
jax/cs/storage/object/services/https/__init__.py
jax/cs/storage/object/services/io/__init__.py
jax/cs/storage/object/services/io/service.py
jax/cs/storage/object/services/r2/__init__.py
jax/cs/storage/object/services/r2/service.py
jax/cs/storage/object/services/r2/utils.py
jax/cs/storage/utils.py
jax_cs_storage-0.10.0.dist-info/LICENSE
jax_cs_storage-0.10.0.dist-info/METADATA
jax_cs_storage-0.10.0.dist-info/WHEEL
jax_cs_storage-0.10.0.dist-info/RECORD
