Metadata-Version: 2.3
Name: jax-cs-storage
Version: 0.10.0
Summary: A python wrapper to make file backends seamless
License: Apache-2.0
Author: Alexander Berger
Author-email: Alexander.Berger@jax.org
Requires-Python: >=3.8,<4.0
Classifier: License :: OSI Approved :: Apache Software License
Classifier: Programming Language :: Python :: 3
Classifier: Programming Language :: Python :: 3.8
Classifier: Programming Language :: Python :: 3.9
Classifier: Programming Language :: Python :: 3.10
Classifier: Programming Language :: Python :: 3.11
Classifier: Programming Language :: Python :: 3.12
Classifier: Programming Language :: Python :: 3.13
Requires-Dist: google-cloud-storage (>=2.5.0,<3.0.0)
Requires-Dist: importlib-metadata (>=1.0,<2.0) ; python_version < "3.8"
Requires-Dist: pydantic (>=2.5.1,<3.0.0)
Requires-Dist: pydantic-settings (>=2.1.0,<3.0.0)
Requires-Dist: requests (>=2.20,<3.0)
Project-URL: Repository, https://bitbucket.org/jacksonlaboratory/jax-cs-storage/
